{"picks": [{"player": "Emam Ashour", "country": "Egypt", "flag": "🇪🇬", "marketId": "player_shot_on_target", "marketLabel": "Tiro al arco", "market": "Tiro al arco", "line": "over 0.5 tiros al arco", "odds": 2.16, "confidence": "HIGH", "confidenceScore": 87, "statBacking": "2.0 tiros al arco/partido vs promedio 0.7 para su posición", "probability": 0.52, "scope": "player"}, {"player": "N. Raskin", "country": "Belgium", "flag": "🇧🇪", "marketId": "player_yellow_card", "marketLabel": "Amarilla", "market": "Amarilla", "line": "recibe tarjeta amarilla", "odds": 1.86, "confidence": "MEDIUM", "confidenceScore": 69, "statBacking": "1 amarilla cada 4 partidos (promedio: cada 8)", "probability": 0.57, "scope": "player"}, {"player": "A. Saelemaekers", "country": "Belgium", "flag": "🇧🇪", "marketId": "player_yellow_card", "marketLabel": "Amarilla", "market": "Amarilla", "line": "recibe tarjeta amarilla", "odds": 2.08, "confidence": "MEDIUM", "confidenceScore": 64, "statBacking": "1 amarilla cada 5 partidos (promedio: cada 8)", "probability": 0.51, "scope": "player"}, {"player": "H. Vanaken", "country": "Belgium", "flag": "🇧🇪", "marketId": "player_tackle", "marketLabel": "Tackles", "market": "Tackles", "line": "over 1.5 tackles", "odds": 1.81, "confidence": "MEDIUM", "confidenceScore": 64, "statBacking": "Mediocampista con 3.3 asistencias c/10 partidos", "probability": 0.58, "scope": "player"}, {"player": "Karim Hafez", "country": "Egypt", "flag": "🇪🇬", "marketId": "player_yellow_card", "marketLabel": "Amarilla", "market": "Amarilla", "line": "recibe tarjeta amarilla", "odds": 2.22, "confidence": "MEDIUM", "confidenceScore": 62, "statBacking": "1 amarilla cada 4 partidos (promedio: cada 8)", "probability": 0.51, "scope": "player"}], "combos": [{"id": "cp-cmq304vb", "name": "Doble con respaldo estadístico", "description": "Las dos señales de mayor confianza del partido combinadas.", "riskLevel": "MODERADO", "picks": [{"player": "Emam Ashour", "country": "Egypt", "flag": "🇪🇬", "marketId": "player_shot_on_target", "marketLabel": "Tiro al arco", "market": "Tiro al arco", "line": "over 0.5 tiros al arco", "odds": 2.16, "confidence": "HIGH", "confidenceScore": 87, "statBacking": "2.0 tiros al arco/partido vs promedio 0.7 para su posición", "probability": 0.52, "scope": "player"}, {"player": "N. Raskin", "country": "Belgium", "flag": "🇧🇪", "marketId": "player_yellow_card", "marketLabel": "Amarilla", "market": "Amarilla", "line": "recibe tarjeta amarilla", "odds": 1.86, "confidence": "MEDIUM", "confidenceScore": 69, "statBacking": "1 amarilla cada 4 partidos (promedio: cada 8)", "probability": 0.57, "scope": "player"}], "totalOdds": 4.02, "combinedScore": 78, "estimatedProbability": 30}]}