{"picks": [{"player": "H. Boudaoui", "country": "Algeria", "flag": "🇩🇿", "marketId": "player_yellow_card", "marketLabel": "Amarilla", "market": "Amarilla", "line": "recibe tarjeta amarilla", "odds": 1.93, "confidence": "MEDIUM", "confidenceScore": 62, "statBacking": "1 amarilla cada 3 partidos (promedio: cada 8)", "probability": 0.62, "scope": "player"}, {"player": "Mohannad Abu Taha", "country": "Jordan", "flag": "🇯🇴", "marketId": "player_tackle", "marketLabel": "Tackles", "market": "Tackles", "line": "over 1.5 tackles", "odds": 1.63, "confidence": "MEDIUM", "confidenceScore": 63, "statBacking": "Defensor con 1.7 goles c/10 partidos — cuotas ofensivas altas", "probability": 0.69, "scope": "player"}], "combos": [{"id": "cp-cmq304vc", "name": "Doble con respaldo estadístico", "description": "Las dos señales de mayor confianza del partido combinadas.", "riskLevel": "MODERADO", "picks": [{"player": "H. Boudaoui", "country": "Algeria", "flag": "🇩🇿", "marketId": "player_yellow_card", "marketLabel": "Amarilla", "market": "Amarilla", "line": "recibe tarjeta amarilla", "odds": 1.93, "confidence": "MEDIUM", "confidenceScore": 62, "statBacking": "1 amarilla cada 3 partidos (promedio: cada 8)", "probability": 0.62, "scope": "player"}, {"player": "Mohannad Abu Taha", "country": "Jordan", "flag": "🇯🇴", "marketId": "player_tackle", "marketLabel": "Tackles", "market": "Tackles", "line": "over 1.5 tackles", "odds": 1.63, "confidence": "MEDIUM", "confidenceScore": 63, "statBacking": "Defensor con 1.7 goles c/10 partidos — cuotas ofensivas altas", "probability": 0.69, "scope": "player"}], "totalOdds": 3.15, "combinedScore": 62, "estimatedProbability": 0.43}]}